dragon_eval/__init__.py
dragon_eval/__main__.py
dragon_eval/evaluation.py
dragon_eval/redaction_score.py
dragon_eval/evalutils/__init__.py
dragon_eval/evalutils/evalutils.py
dragon_eval/evalutils/exceptions.py
dragon_eval/evalutils/io.py
dragon_eval/evalutils/validators.py
dragon_eval-0.2.11.dist-info/licenses/LICENSE
dragon_eval-0.2.11.dist-info/METADATA
dragon_eval-0.2.11.dist-info/WHEEL
dragon_eval-0.2.11.dist-info/top_level.txt
dragon_eval-0.2.11.dist-info/RECORD
