Metadata-Version: 2.4
Name: dragon_eval
Version: 0.2.11
Summary: Evaluation method for the DRAGON benchmark
Home-page: https://github.com/DIAGNijmegen/dragon_eval
Author: Joeran Bosma
Author-email: Joeran.Bosma@radboudumc.nl
Project-URL: Bug Tracker, https://github.com/DIAGNijmegen/dragon_eval/issues
Platform: unix
Platform: linux
Platform: osx
Platform: cygwin
Platform: win32
Classifier: Programming Language :: Python :: 3
Classifier: Programming Language :: Python :: 3 :: Only
Classifier: Programming Language :: Python :: 3.8
Classifier: Programming Language :: Python :: 3.9
Classifier: Programming Language :: Python :: 3.10
Classifier: Programming Language :: Python :: 3.11
Classifier: Programming Language :: Python :: 3.12
Requires-Python: >=3.7
License-File: LICENSE
Requires-Dist: numpy
Requires-Dist: pandas
Requires-Dist: seqeval
Requires-Dist: scikit-learn
Provides-Extra: testing
Requires-Dist: pytest>=6.0; extra == "testing"
Requires-Dist: pytest-cov>=2.0; extra == "testing"
Requires-Dist: mypy>=0.910; extra == "testing"
Requires-Dist: flake8>=3.9; extra == "testing"
Requires-Dist: tox>=3.24; extra == "testing"
Dynamic: author-email
Dynamic: description
Dynamic: description-content-type
Dynamic: home-page
Dynamic: license-file
Dynamic: project-url
